{
  "color-space-for-untagged-svg-colors" : "display-p3",
  "fill" : {
    "linear-gradient" : [
      "srgb:0.00000,0.40000,1.00000,1.00000",
      "display-p3:0.00000,0.30000,0.75000,1.00000"
    ]
  },
  "groups" : [
    {
      "blend-mode" : "overlay",
      "blur-material" : 0,
      "hidden" : false,
      "layers" : [
        {
          "hidden" : false,
          "image-name" : "bars.svg",
          "name" : "bars",
          "position" : {
            "scale" : 1.04,
            "translation-in-points" : [
              0,
              0
            ]
          }
        }
      ],
      "lighting" : "individual",
      "name" : "Bars",
      "opacity" : 0.5,
      "shadow" : {
        "kind" : "layer-color",
        "opacity" : 0
      },
      "specular" : true,
      "translucency" : {
        "enabled" : true,
        "value" : 1
      }
    },
    {
      "blend-mode" : "normal",
      "blur-material" : 0.75,
      "hidden" : false,
      "layers" : [
        {
          "image-name" : "bars.svg",
          "name" : "bars",
          "position" : {
            "scale" : 1.04,
            "translation-in-points" : [
              0,
              0
            ]
          }
        }
      ],
      "lighting" : "individual",
      "name" : "Bars",
      "shadow" : {
        "kind" : "layer-color",
        "opacity" : 0.5
      },
      "specular" : true,
      "translucency" : {
        "enabled" : true,
        "value" : 0.2
      }
    },
    {
      "blur-material" : 0.7,
      "layers" : [
        {
          "image-name" : "bars back.svg",
          "name" : "bars back",
          "position" : {
            "scale" : 1.04,
            "translation-in-points" : [
              0,
              0
            ]
          }
        }
      ],
      "shadow" : {
        "kind" : "layer-color",
        "opacity" : 0.25
      },
      "specular" : true,
      "translucency" : {
        "enabled" : true,
        "value" : 0.45000000000000007
      }
    }
  ],
  "supported-platforms" : {
    "squares" : "shared"
  }
}